wespipeline/__init__.py
wespipeline/align.py
wespipeline/fastq.py
wespipeline/processalign.py
wespipeline/reference.py
wespipeline/utils.py
wespipeline/vcf.py
wespipeline/vcfanalysis.py
wespipeline-1.0.1.dist-info/LICENSE
wespipeline-1.0.1.dist-info/METADATA
wespipeline-1.0.1.dist-info/WHEEL
wespipeline-1.0.1.dist-info/top_level.txt
wespipeline-1.0.1.dist-info/RECORD
