Metadata-Version: 2.1
Name: wespipeline
Version: 1.0.1
Summary: An implementation of a whole exome analysis pipeline using the library Luigi for workflow management.
Home-page: UNKNOWN
Author: Alejandro Rodríguez Díaz
Author-email: jancho@usal.es
License: UNKNOWN
Project-URL: Documentation, https://wespipeline.readthedocs.io/en/latest/index.html
Project-URL: Source, https://github.com/Janchorizo/wespipeline
Project-URL: Tracker, https://github.com/Janchorizo/wespipeline/issues
Platform: UNKNOWN
Classifier: Programming Language :: Python :: 3
Classifier: License :: OSI Approved :: MIT License
Classifier: Operating System :: OS Independent
Requires-Python: >=3.6
Requires-Dist: luigi
Requires-Dist: docker
Requires-Dist: python-daemon
